rizzless_guitar_guide/__init__.py
rizzless_guitar_guide/guide.py
rizzless_guitar_guide/intervalstuff.py
rizzless_guitar_guide/modestuff.py
rizzless_guitar_guide/scalestuff.py
rizzless_guitar_guide-1.0.1a0.dist-info/METADATA
rizzless_guitar_guide-1.0.1a0.dist-info/WHEEL
rizzless_guitar_guide-1.0.1a0.dist-info/licenses/LICENSE.txt
rizzless_guitar_guide-1.0.1a0.dist-info/RECORD
