Metadata-Version: 2.1
Name: rizzless_guitar_guide
Version: 1.0.1a0
Summary: Reduced nesting, topics can now be searched upon launch
Project-URL: Homepage, https://github.com/captainrizzless/musical-practice-stuff
Project-URL: Bug Tracker, https://github.com/captainrizzless/musical-practice-stuff/issues
Author-email: Michael Lacy <michaellacy21419@gmail.com>
License-File: LICENSE.txt
Classifier: License :: OSI Approved :: MIT License
Classifier: Operating System :: OS Independent
Classifier: Programming Language :: Python :: 3
Requires-Python: >=3.11
